{
  "webhintio/hint": [
    {
      "date": "2022-02-28",
      "rate": "86.67"
    },
    {
      "date": "2022-03-01",
      "rate": "83.33"
    },
    {
      "date": "2022-03-02",
      "rate": "83.33"
    },
    {
      "date": "2022-03-03",
      "rate": "83.33"
    },
    {
      "date": "2022-03-04",
      "rate": "83.33"
    },
    {
      "date": "2022-03-05",
      "rate": "83.33"
    },
    {
      "date": "2022-03-06",
      "rate": "83.33"
    },
    {
      "date": "2022-03-07",
      "rate": "83.33"
    },
    {
      "date": "2022-03-08",
      "rate": "80"
    },
    {
      "date": "2022-03-09",
      "rate": "90"
    },
    {
      "date": "2022-03-10",
      "rate": "90"
    },
    {
      "date": "2022-03-11",
      "unRespondedItems": [
        {
          "title": "[Bug] Cross-origin resource needs a 'crossorigin' attribute even though crossorigin is specified",
          "url": "https://github.com/webhintio/hint/issues/5054"
        },
        {
          "title": "[Bug] Does not seems to support `extends` from tsconfig.json",
          "url": "https://github.com/webhintio/hint/issues/5035"
        },
        {
          "title": "[Bug][Intrusive] keep on `npm install hint@latest` on opening folder",
          "url": "https://github.com/webhintio/hint/issues/5034"
        },
        {
          "title": "[Bug][VS Code extension] Environment variables are not respected",
          "url": "https://github.com/webhintio/hint/issues/4957"
        },
        {
          "title": "Breaking: Raise min required node version to 14",
          "url": "https://github.com/webhintio/hint/pull/4886"
        }
      ],
      "rate": "90.00"
    },
    {
      "date": "2022-03-12",
      "unRespondedItems": [
        {
          "title": "Extension suddenly stopped working: e is undefined",
          "url": "https://github.com/webhintio/hint/issues/5078"
        },
        {
          "title": "[Bug] Cross-origin resource needs a 'crossorigin' attribute even though crossorigin is specified",
          "url": "https://github.com/webhintio/hint/issues/5054"
        },
        {
          "title": "[Bug] Does not seems to support `extends` from tsconfig.json",
          "url": "https://github.com/webhintio/hint/issues/5035"
        },
        {
          "title": "[Bug][Intrusive] keep on `npm install hint@latest` on opening folder",
          "url": "https://github.com/webhintio/hint/issues/5034"
        },
        {
          "title": "[Bug][VS Code extension] Environment variables are not respected",
          "url": "https://github.com/webhintio/hint/issues/4957"
        },
        {
          "title": "Breaking: Raise min required node version to 14",
          "url": "https://github.com/webhintio/hint/pull/4886"
        }
      ],
      "rate": "88.00"
    },
    {
      "date": "2022-03-13",
      "unRespondedItems": [
        {
          "title": "Extension suddenly stopped working: e is undefined",
          "url": "https://github.com/webhintio/hint/issues/5078"
        },
        {
          "title": "[Bug] Cross-origin resource needs a 'crossorigin' attribute even though crossorigin is specified",
          "url": "https://github.com/webhintio/hint/issues/5054"
        },
        {
          "title": "[Bug] Does not seems to support `extends` from tsconfig.json",
          "url": "https://github.com/webhintio/hint/issues/5035"
        },
        {
          "title": "[Bug][Intrusive] keep on `npm install hint@latest` on opening folder",
          "url": "https://github.com/webhintio/hint/issues/5034"
        },
        {
          "title": "[Bug][VS Code extension] Environment variables are not respected",
          "url": "https://github.com/webhintio/hint/issues/4957"
        },
        {
          "title": "Breaking: Raise min required node version to 14",
          "url": "https://github.com/webhintio/hint/pull/4886"
        }
      ],
      "rate": "88.00"
    },
    {
      "date": "2022-03-14",
      "unRespondedItems": [
        {
          "title": "Extension suddenly stopped working: e is undefined",
          "url": "https://github.com/webhintio/hint/issues/5078"
        },
        {
          "title": "[Bug] Cross-origin resource needs a 'crossorigin' attribute even though crossorigin is specified",
          "url": "https://github.com/webhintio/hint/issues/5054"
        },
        {
          "title": "[Bug] Does not seems to support `extends` from tsconfig.json",
          "url": "https://github.com/webhintio/hint/issues/5035"
        },
        {
          "title": "[Bug][Intrusive] keep on `npm install hint@latest` on opening folder",
          "url": "https://github.com/webhintio/hint/issues/5034"
        },
        {
          "title": "[Bug][VS Code extension] Environment variables are not respected",
          "url": "https://github.com/webhintio/hint/issues/4957"
        },
        {
          "title": "Breaking: Raise min required node version to 14",
          "url": "https://github.com/webhintio/hint/pull/4886"
        }
      ],
      "rate": "88.00"
    }
  ],
  "MicrosoftEdge/demos": [
    {
      "date": "2022-02-28",
      "rate": "100"
    },
    {
      "date": "2022-03-01",
      "rate": "100"
    },
    {
      "date": "2022-03-02",
      "rate": "100"
    },
    {
      "date": "2022-03-03",
      "rate": "100"
    },
    {
      "date": "2022-03-04",
      "rate": "100"
    },
    {
      "date": "2022-03-05",
      "rate": "100"
    },
    {
      "date": "2022-03-06",
      "rate": "100"
    },
    {
      "date": "2022-03-07",
      "rate": "100"
    },
    {
      "date": "2022-03-08",
      "rate": "100"
    },
    {
      "date": "2022-03-09",
      "rate": "100"
    },
    {
      "date": "2022-03-10",
      "rate": "100"
    },
    {
      "date": "2022-03-11",
      "unRespondedItems": [],
      "rate": "100.00"
    },
    {
      "date": "2022-03-12",
      "unRespondedItems": [],
      "rate": 100
    },
    {
      "date": "2022-03-13",
      "unRespondedItems": [],
      "rate": 100
    },
    {
      "date": "2022-03-14",
      "unRespondedItems": [],
      "rate": 100
    }
  ],
  "MicrosoftEdge/DevTools": [
    {
      "date": "2022-02-28",
      "rate": "100"
    },
    {
      "date": "2022-03-01",
      "rate": "100"
    },
    {
      "date": "2022-03-02",
      "rate": "50"
    },
    {
      "date": "2022-03-03",
      "rate": "60"
    },
    {
      "date": "2022-03-04",
      "rate": "60"
    },
    {
      "date": "2022-03-05",
      "rate": "60"
    },
    {
      "date": "2022-03-06",
      "rate": "60"
    },
    {
      "date": "2022-03-07",
      "rate": "60"
    },
    {
      "date": "2022-03-08",
      "rate": "28.57"
    },
    {
      "date": "2022-03-09",
      "rate": "41.18"
    },
    {
      "date": "2022-03-10",
      "rate": "63.16"
    },
    {
      "date": "2022-03-11",
      "unRespondedItems": [
        {
          "title": "Microsoft Editor integration in dev tools",
          "url": "https://github.com/MicrosoftEdge/DevTools/issues/21"
        },
        {
          "title": "Simulate low memory or throttle memory like how DevTools can throttle CPU",
          "url": "https://github.com/MicrosoftEdge/DevTools/issues/12"
        },
        {
          "title": "Create a view for Dominators in the Memory tool",
          "url": "https://github.com/MicrosoftEdge/DevTools/issues/7"
        },
        {
          "title": "When taking a heap snapshot, dump all string values to a file or view",
          "url": "https://github.com/MicrosoftEdge/DevTools/issues/6"
        },
        {
          "title": "[Feedback] Retrieve source maps from Symbol Server",
          "url": "https://github.com/MicrosoftEdge/DevTools/issues/5"
        },
        {
          "title": "Sort styles alphabetically",
          "url": "https://github.com/MicrosoftEdge/DevTools/issues/19"
        },
        {
          "title": "enable-throttle-display-none-and-visibility-hidden-cross-origin-iframes flag",
          "url": "https://github.com/MicrosoftEdge/DevTools/issues/3"
        }
      ],
      "rate": "65.00"
    },
    {
      "date": "2022-03-12",
      "unRespondedItems": [],
      "rate": 100
    },
    {
      "date": "2022-03-13",
      "unRespondedItems": [],
      "rate": 100
    },
    {
      "date": "2022-03-14",
      "unRespondedItems": [],
      "rate": 100
    }
  ],
  "MicrosoftEdge/EdgeWebDriver": [
    {
      "date": "2022-02-28",
      "rate": "100"
    },
    {
      "date": "2022-03-01",
      "rate": "100"
    },
    {
      "date": "2022-03-02",
      "rate": "100"
    },
    {
      "date": "2022-03-03",
      "rate": "100"
    },
    {
      "date": "2022-03-04",
      "rate": "100"
    },
    {
      "date": "2022-03-05",
      "rate": "100"
    },
    {
      "date": "2022-03-06",
      "rate": "100"
    },
    {
      "date": "2022-03-07",
      "rate": "100"
    },
    {
      "date": "2022-03-08",
      "rate": "25"
    },
    {
      "date": "2022-03-09",
      "rate": "25"
    },
    {
      "date": "2022-03-10",
      "rate": "25"
    },
    {
      "date": "2022-03-11",
      "unRespondedItems": [
        {
          "title": "Refactor classic EdgeDriver server",
          "url": "https://github.com/MicrosoftEdge/EdgeWebDriver/issues/4"
        },
        {
          "title": "Integrate Chromium BiDi implementation in the Edge browser",
          "url": "https://github.com/MicrosoftEdge/EdgeWebDriver/issues/3"
        },
        {
          "title": "Microsoft Edge WebDriver should update to keep in sync with the Edge browser",
          "url": "https://github.com/MicrosoftEdge/EdgeWebDriver/issues/2"
        }
      ],
      "rate": "25.00"
    },
    {
      "date": "2022-03-12",
      "unRespondedItems": [],
      "rate": 100
    },
    {
      "date": "2022-03-13",
      "unRespondedItems": [],
      "rate": 100
    },
    {
      "date": "2022-03-14",
      "unRespondedItems": [],
      "rate": 100
    }
  ],
  "MicrosoftEdge/WebView2Feedback": [
    {
      "date": "2022-02-28",
      "rate": "13.33"
    },
    {
      "date": "2022-03-01",
      "rate": "60"
    },
    {
      "date": "2022-03-02",
      "rate": "56.67"
    },
    {
      "date": "2022-03-03",
      "rate": "73.33"
    },
    {
      "date": "2022-03-04",
      "rate": "73.33"
    },
    {
      "date": "2022-03-05",
      "rate": "60"
    },
    {
      "date": "2022-03-06",
      "rate": "56.67"
    },
    {
      "date": "2022-03-07",
      "rate": "50"
    },
    {
      "date": "2022-03-08",
      "rate": "63.33"
    },
    {
      "date": "2022-03-09",
      "rate": "80"
    },
    {
      "date": "2022-03-10",
      "rate": "83.33"
    },
    {
      "date": "2022-03-11",
      "unRespondedItems": [
        {
          "title": "WebView2 freeze when activating WebRTC sharing notification ",
          "url": "https://github.com/MicrosoftEdge/WebView2Feedback/issues/2258"
        },
        {
          "title": "Passing POST headers through WebResourceRequested and CreateWebResourceRequest content is null exception",
          "url": "https://github.com/MicrosoftEdge/WebView2Feedback/issues/2250"
        },
        {
          "title": "OKTA server login attempt stuck in a loop in a re-entrant scenario",
          "url": "https://github.com/MicrosoftEdge/WebView2Feedback/issues/2229"
        },
        {
          "title": "Throw custom exception for WebView Control is no longer valid",
          "url": "https://github.com/MicrosoftEdge/WebView2Feedback/issues/2254"
        },
        {
          "title": "On WebView getting disposed, it hangs the rendering thread - without any possibility for restoring it",
          "url": "https://github.com/MicrosoftEdge/WebView2Feedback/issues/2247"
        },
        {
          "title": "Microsoft IME candidates window open in wrong place",
          "url": "https://github.com/MicrosoftEdge/WebView2Feedback/issues/2241"
        },
        {
          "title": "Windows 7 not working due to `EventSetInformation`",
          "url": "https://github.com/MicrosoftEdge/WebView2Feedback/issues/2227"
        },
        {
          "title": "Signed exe doesn't work",
          "url": "https://github.com/MicrosoftEdge/WebView2Feedback/issues/2212"
        },
        {
          "title": "Windows 10 64Bit Silent Evergreen install fails with 0x80040719",
          "url": "https://github.com/MicrosoftEdge/WebView2Feedback/issues/2204"
        }
      ],
      "rate": "82.00"
    },
    {
      "date": "2022-03-12",
      "unRespondedItems": [],
      "rate": 100
    },
    {
      "date": "2022-03-13",
      "unRespondedItems": [],
      "rate": 100
    },
    {
      "date": "2022-03-14",
      "unRespondedItems": [],
      "rate": 100
    }
  ],
  "MicrosoftEdge/WebView2Samples": [
    {
      "date": "2022-02-28",
      "rate": "70"
    },
    {
      "date": "2022-03-01",
      "rate": "70"
    },
    {
      "date": "2022-03-02",
      "rate": "70"
    },
    {
      "date": "2022-03-03",
      "rate": "70"
    },
    {
      "date": "2022-03-04",
      "rate": "70"
    },
    {
      "date": "2022-03-05",
      "rate": "70"
    },
    {
      "date": "2022-03-06",
      "rate": "70"
    },
    {
      "date": "2022-03-07",
      "rate": "70"
    },
    {
      "date": "2022-03-08",
      "rate": "70"
    },
    {
      "date": "2022-03-09",
      "rate": "70"
    },
    {
      "date": "2022-03-10",
      "rate": "70"
    },
    {
      "date": "2022-03-11",
      "unRespondedItems": [
        {
          "title": "Build error in Windows Implementation library resource.h",
          "url": "https://github.com/MicrosoftEdge/WebView2Samples/issues/108"
        },
        {
          "title": "Call Navigate return  -2147019873?",
          "url": "https://github.com/MicrosoftEdge/WebView2Samples/issues/90"
        },
        {
          "title": "Is there another way to replace Microsoft::WRL::Callback?",
          "url": "https://github.com/MicrosoftEdge/WebView2Samples/issues/88"
        },
        {
          "title": "Compilation error - tried with SDK verions - ",
          "url": "https://github.com/MicrosoftEdge/WebView2Samples/issues/82"
        },
        {
          "title": "How to get page security info",
          "url": "https://github.com/MicrosoftEdge/WebView2Samples/issues/80"
        },
        {
          "title": "Vanilla Download of WV2 Has Errors in the project WebView2WindowsFormsBrowser ",
          "url": "https://github.com/MicrosoftEdge/WebView2Samples/issues/72"
        },
        {
          "title": "Wpf Permissions for Push Notification Sample",
          "url": "https://github.com/MicrosoftEdge/WebView2Samples/issues/37"
        },
        {
          "title": "Error Loading Winforms Sample: Project file is incomplete. Expected imports are missing.",
          "url": "https://github.com/MicrosoftEdge/WebView2Samples/issues/36"
        },
        {
          "title": "Need Webview2 Sample For vb6,vba,python,vbs(Webview2  For Visualbasic6.0)",
          "url": "https://github.com/MicrosoftEdge/WebView2Samples/issues/96"
        },
        {
          "title": "Just say no to wil::com_ptr",
          "url": "https://github.com/MicrosoftEdge/WebView2Samples/issues/76"
        },
        {
          "title": "How to setup a CallCallbackAsynchronously on C#",
          "url": "https://github.com/MicrosoftEdge/WebView2Samples/issues/66"
        },
        {
          "title": "Javascript bridge window.external.notify",
          "url": "https://github.com/MicrosoftEdge/WebView2Samples/issues/43"
        },
        {
          "title": "cppwinrt Callback",
          "url": "https://github.com/MicrosoftEdge/WebView2Samples/issues/30"
        },
        {
          "title": "UWP Sample",
          "url": "https://github.com/MicrosoftEdge/WebView2Samples/issues/28"
        }
      ],
      "rate": "72.00"
    },
    {
      "date": "2022-03-12",
      "unRespondedItems": [],
      "rate": 100
    },
    {
      "date": "2022-03-13",
      "unRespondedItems": [],
      "rate": 100
    },
    {
      "date": "2022-03-14",
      "unRespondedItems": [],
      "rate": 100
    }
  ],
  "MicrosoftEdge/WebView2Browser": [
    {
      "date": "2022-02-28",
      "rate": "55.17"
    },
    {
      "date": "2022-03-01",
      "rate": "55.17"
    },
    {
      "date": "2022-03-02",
      "rate": "55.17"
    },
    {
      "date": "2022-03-03",
      "rate": "55.17"
    },
    {
      "date": "2022-03-04",
      "rate": "55.17"
    },
    {
      "date": "2022-03-05",
      "rate": "55.17"
    },
    {
      "date": "2022-03-06",
      "rate": "55.17"
    },
    {
      "date": "2022-03-07",
      "rate": "55.17"
    },
    {
      "date": "2022-03-08",
      "rate": "55.17"
    },
    {
      "date": "2022-03-09",
      "rate": "55.17"
    },
    {
      "date": "2022-03-10",
      "rate": "55.17"
    },
    {
      "date": "2022-03-11",
      "unRespondedItems": [
        {
          "title": "Policy \"NewTabPageManagedQuickLinks\" error when more that 3 entries",
          "url": "https://github.com/MicrosoftEdge/WebView2Browser/issues/37"
        },
        {
          "title": "warning MSB8004: Output Directory does not end with a trailing slash.  This build instance will add the slash as it is required to allow proper evaluation of the Output Directory.",
          "url": "https://github.com/MicrosoftEdge/WebView2Browser/issues/33"
        },
        {
          "title": "Save / Update Password prompts do not work",
          "url": "https://github.com/MicrosoftEdge/WebView2Browser/issues/32"
        },
        {
          "title": "Why is nobody talking HTA here?",
          "url": "https://github.com/MicrosoftEdge/WebView2Browser/issues/26"
        },
        {
          "title": "NullReferenceException at startup",
          "url": "https://github.com/MicrosoftEdge/WebView2Browser/issues/24"
        },
        {
          "title": "Downloads appear to be unsupported at this time.",
          "url": "https://github.com/MicrosoftEdge/WebView2Browser/issues/23"
        },
        {
          "title": "Overlay issue of other controls.",
          "url": "https://github.com/MicrosoftEdge/WebView2Browser/issues/22"
        },
        {
          "title": "Does it support to use plugin in webview2 ?",
          "url": "https://github.com/MicrosoftEdge/WebView2Browser/issues/15"
        },
        {
          "title": "Does not work with the latest Canary / Development version.",
          "url": "https://github.com/MicrosoftEdge/WebView2Browser/issues/11"
        },
        {
          "title": "Does not build",
          "url": "https://github.com/MicrosoftEdge/WebView2Browser/issues/9"
        },
        {
          "title": "OpenSource declaration",
          "url": "https://github.com/MicrosoftEdge/WebView2Browser/issues/5"
        },
        {
          "title": "Memory Usage in Task Manager",
          "url": "https://github.com/MicrosoftEdge/WebView2Browser/issues/4"
        },
        {
          "title": "How to create new tab dynamically on ICoreWebView2NewWindowRequestedEventHandler event? ",
          "url": "https://github.com/MicrosoftEdge/WebView2Browser/issues/29"
        }
      ],
      "rate": "55.17"
    },
    {
      "date": "2022-03-12",
      "unRespondedItems": [],
      "rate": 100
    },
    {
      "date": "2022-03-13",
      "unRespondedItems": [],
      "rate": 100
    },
    {
      "date": "2022-03-14",
      "unRespondedItems": [],
      "rate": 100
    }
  ],
  "microsoft/vscode-edge-devtools": [
    {
      "date": "2022-02-28",
      "rate": "83.33"
    },
    {
      "date": "2022-03-01",
      "rate": "90"
    },
    {
      "date": "2022-03-02",
      "rate": "90"
    },
    {
      "date": "2022-03-03",
      "rate": "80"
    },
    {
      "date": "2022-03-04",
      "rate": "80"
    },
    {
      "date": "2022-03-05",
      "rate": "83.33"
    },
    {
      "date": "2022-03-06",
      "rate": "80"
    },
    {
      "date": "2022-03-07",
      "rate": "86.67"
    },
    {
      "date": "2022-03-08",
      "rate": "90"
    },
    {
      "date": "2022-03-09",
      "rate": "90"
    },
    {
      "date": "2022-03-10",
      "rate": "80"
    },
    {
      "date": "2022-03-11",
      "unRespondedItems": [
        {
          "title": "Update  vscode-webhint to version 1.6.5",
          "url": "https://github.com/microsoft/vscode-edge-devtools/pull/920"
        },
        {
          "title": "Add Support for Vue, React, Angular frameworks",
          "url": "https://github.com/microsoft/vscode-edge-devtools/issues/919"
        },
        {
          "title": "Vertical Scaling",
          "url": "https://github.com/microsoft/vscode-edge-devtools/issues/908"
        },
        {
          "title": "Javascript debugger does not connect to headless instance",
          "url": "https://github.com/microsoft/vscode-edge-devtools/issues/896"
        },
        {
          "title": "Issue while adding a New Style Rule",
          "url": "https://github.com/microsoft/vscode-edge-devtools/issues/872"
        }
      ],
      "rate": "90.00"
    },
    {
      "date": "2022-03-12",
      "unRespondedItems": [
        {
          "title": "Add Support for Vue, React, Angular frameworks",
          "url": "https://github.com/microsoft/vscode-edge-devtools/issues/919"
        },
        {
          "title": "Vertical Scaling",
          "url": "https://github.com/microsoft/vscode-edge-devtools/issues/908"
        },
        {
          "title": "Javascript debugger does not connect to headless instance",
          "url": "https://github.com/microsoft/vscode-edge-devtools/issues/896"
        },
        {
          "title": "Issue while adding a New Style Rule",
          "url": "https://github.com/microsoft/vscode-edge-devtools/issues/872"
        }
      ],
      "rate": "92.00"
    },
    {
      "date": "2022-03-13",
      "unRespondedItems": [
        {
          "title": "Microsoft / vscode-edge-devtools",
          "url": "https://github.com/microsoft/vscode-edge-devtools/issues/923"
        },
        {
          "title": "Add Support for Vue, React, Angular frameworks",
          "url": "https://github.com/microsoft/vscode-edge-devtools/issues/919"
        },
        {
          "title": "Vertical Scaling",
          "url": "https://github.com/microsoft/vscode-edge-devtools/issues/908"
        },
        {
          "title": "Javascript debugger does not connect to headless instance",
          "url": "https://github.com/microsoft/vscode-edge-devtools/issues/896"
        },
        {
          "title": "Issue while adding a New Style Rule",
          "url": "https://github.com/microsoft/vscode-edge-devtools/issues/872"
        }
      ],
      "rate": "90.00"
    },
    {
      "date": "2022-03-14",
      "unRespondedItems": [
        {
          "title": "Microsoft / vscode-edge-devtools",
          "url": "https://github.com/microsoft/vscode-edge-devtools/issues/923"
        },
        {
          "title": "Add Support for Vue, React, Angular frameworks",
          "url": "https://github.com/microsoft/vscode-edge-devtools/issues/919"
        },
        {
          "title": "Vertical Scaling",
          "url": "https://github.com/microsoft/vscode-edge-devtools/issues/908"
        },
        {
          "title": "Javascript debugger does not connect to headless instance",
          "url": "https://github.com/microsoft/vscode-edge-devtools/issues/896"
        },
        {
          "title": "Issue while adding a New Style Rule",
          "url": "https://github.com/microsoft/vscode-edge-devtools/issues/872"
        }
      ],
      "rate": "90.00"
    }
  ],
  "MicrosoftDocs/edge-developer": [
    {
      "date": "2022-02-28",
      "rate": "100"
    },
    {
      "date": "2022-03-01",
      "rate": "100"
    },
    {
      "date": "2022-03-02",
      "rate": "100"
    },
    {
      "date": "2022-03-03",
      "rate": "100"
    },
    {
      "date": "2022-03-04",
      "rate": "100"
    },
    {
      "date": "2022-03-05",
      "rate": "100"
    },
    {
      "date": "2022-03-06",
      "rate": "100"
    },
    {
      "date": "2022-03-07",
      "rate": "100"
    },
    {
      "date": "2022-03-08",
      "rate": "100"
    },
    {
      "date": "2022-03-09",
      "rate": "100"
    },
    {
      "date": "2022-03-10",
      "rate": "100"
    },
    {
      "date": "2022-03-11",
      "unRespondedItems": [
        {
          "title": "ReleaseNote for WebView2 Edge99",
          "url": "https://github.com/MicrosoftDocs/edge-developer/pull/1793"
        },
        {
          "title": "Removed suggestion to use twitter to contact the team",
          "url": "https://github.com/MicrosoftDocs/edge-developer/pull/1792"
        },
        {
          "title": "Changes to move from private preview to Beta",
          "url": "https://github.com/MicrosoftDocs/edge-developer/pull/1790"
        }
      ],
      "rate": "93.62"
    },
    {
      "date": "2022-03-12",
      "unRespondedItems": [],
      "rate": 100
    },
    {
      "date": "2022-03-13",
      "unRespondedItems": [],
      "rate": 100
    },
    {
      "date": "2022-03-14",
      "unRespondedItems": [],
      "rate": 100
    }
  ]
}